{"0":[{"h":"לַ/מְנַצֵּ֣חַ","t":"la/m.na.Tze.ach","e":"to the/ choirmaster","s":"H5329"},{"h":"אַל־","t":"'al-","e":"al-","s":"H0516"},{"h":"תַּ֭שְׁחֵת","t":"Tash.chet","e":"tashcheth","s":"H0516"},{"h":"לְ/דָוִ֣ד","t":"le./da.Vid","e":"of/ David","s":"H1732"},{"h":"מִכְתָּ֑ם","t":"mikh.Tam","e":"a miktam","s":"H4387"},{"h":"בְּ/בָרְח֥/וֹ","t":"be./va.re.Ch/o","e":"when/ fled/ he","s":"H1272"},{"h":"מִ/פְּנֵי־","t":"mi./pe.nei.Sha-","e":"from/ before","s":"H6440"},{"h":"שָׁ֝א֗וּל","t":"Sha.'Ul","e":"Saul","s":"H7586"},{"h":"בַּ/מְּעָרָֽה׃","t":"ba./me.'a.Rah","e":"in the/ cave","s":"H4631"}],"1":[{"h":"חָנֵּ֤/נִי","t":"cho.ne./ni","e":"show favor to/ me","s":"H2603"},{"h":"אֱלֹהִ֨ים׀","t":"'E.lo.Him","e":"O God","s":"H0430"},{"h":"חָנֵּ֗/נִי","t":"cho.ne./ni","e":"show favor to/ me","s":"H2603"},{"h":"כִּ֥י","t":"ki","e":"for","s":"H3588"},{"h":"בְ/ךָ֮","t":"ve./Kha","e":"in/ you","s":"H9031"},{"h":"חָסָ֪יָה","t":"cha.Sa.yah","e":"it takes refuge","s":"H2620"},{"h":"נַ֫פְשִׁ֥/י","t":"naf.Sh/i","e":"self/ my","s":"H5315"},{"h":"וּ/בְ/צֵֽל־","t":"u./ve./tzel-","e":"and/ in/ [the] shadow of","s":"H6738"},{"h":"כְּנָפֶ֥י/ךָ","t":"ke.na.Fei./kha","e":"wings/ your","s":"H3671"},{"h":"אֶחְסֶ֑ה","t":"'ech.Seh","e":"I take refuge","s":"H2620"},{"h":"עַ֝֗ד","t":"'Ad","e":"until","s":"H5704"},{"h":"יַעֲבֹ֥ר","t":"ya.'a.Vor","e":"it will pass by","s":"H5674"},{"h":"הַוּֽוֹת׃","t":"ha.Vot","e":"destruction","s":"H1942"}],"2":[{"h":"אֶ֭קְרָא","t":"'Ek.ra'","e":"I call out","s":"H7121"},{"h":"לֵֽ/אלֹהִ֣ים","t":"le./lo.Him","e":"to/ God","s":"H0430"},{"h":"עֶלְי֑וֹן","t":"el.Yon","e":"Most High","s":"H5945"},{"h":"לָ֝/אֵ֗ל","t":"la./'El","e":"to / God","s":"H0410"},{"h":"גֹּמֵ֥ר","t":"go.Mer","e":"[who] avenges","s":"H1584"},{"h":"עָלָֽ/י׃","t":"'a.La/i","e":"on/ me","s":"H5921"}],"3":[{"h":"יִשְׁלַ֤ח","t":"yish.Lach","e":"he will send","s":"H7971"},{"h":"מִ/שָּׁמַ֨יִם׀","t":"mi./sha.Ma.yim","e":"from/ heaven","s":"H8064"},{"h":"וְֽ/יוֹשִׁיעֵ֗/נִי","t":"ve./yo.shi.'E./ni","e":"and/ he will save/ me","s":"H3467"},{"h":"חֵרֵ֣ף","t":"che.Ref","e":"he will reproach","s":"H2778"},{"h":"שֹׁאֲפִ֣/י","t":"sho.'a.F/i","e":"[one who] crushes/ me","s":"H7602"},{"h":"סֶ֑לָה","t":"Se.lah","e":"Selah","s":"H5542"},{"h":"יִשְׁלַ֥ח","t":"yish.Lach","e":"he will send","s":"H7971"},{"h":"אֱ֝לֹהִ֗ים","t":"'E.lo.Him","e":"God","s":"H0430"},{"h":"חַסְדּ֥/וֹ","t":"chas.D/o","e":"covenant loyalty/ his","s":"H2617"},{"h":"וַ/אֲמִתּֽ/וֹ׃","t":"va./'a.mi.T/o","e":"and/ faithfulness/ his","s":"H0571"}],"4":[{"h":"נַפְשִׁ֤/י׀","t":"naf.Sh/i","e":"self/ my","s":"H5315"},{"h":"בְּ/ת֥וֹךְ","t":"be./Tokh","e":"in/ among","s":"H8432"},{"h":"לְבָאִם֮","t":"le.va.'Im","e":"lions","s":"H3833"},{"h":"אֶשְׁכְּבָ֪ה","t":"'esh.ke.Vah","e":"I lie with","s":"H7901"},{"h":"לֹ֫הֲטִ֥ים","t":"lo.ha.Tim","e":"[those that] devour","s":"H3857"},{"h":"בְּֽנֵי־","t":"be.nei-","e":"[the] children of","s":"H1121"},{"h":"אָדָ֗ם","t":"'a.Dam","e":"humankind","s":"H0120"},{"h":"שִׁ֭נֵּי/הֶם","t":"Shi.nei./hem","e":"teeth/ their","s":"H8127"},{"h":"חֲנִ֣ית","t":"cha.Nit","e":"[are] a spear","s":"H2595"},{"h":"וְ/חִצִּ֑ים","t":"ve./chi.Tzim","e":"and/ arrows","s":"H2671"},{"h":"וּ֝/לְשׁוֹנָ֗/ם","t":"u./le.sho.Na/m","e":"and/ tongue/ their","s":"H3956"},{"h":"חֶ֣רֶב","t":"Che.rev","e":"[is] a sword","s":"H2719"},{"h":"חַדָּֽה׃","t":"cha.Dah","e":"sharp","s":"H2299"}],"5":[{"h":"ר֣וּמָ/ה","t":"Ru.ma/h","e":"be exalted/ !","s":"H7311"},{"h":"עַל־","t":"'al-","e":"above","s":"H5921"},{"h":"הַ/שָּׁמַ֣יִם","t":"ha./sha.Ma.yim","e":"the/ heavens","s":"H8064"},{"h":"אֱלֹהִ֑ים","t":"'E.lo.Him","e":"O God","s":"H0430"},{"h":"עַ֖ל","t":"'al","e":"[be] over","s":"H5921"},{"h":"כָּל־","t":"kol-","e":"all","s":"H3605"},{"h":"הָ/אָ֣רֶץ","t":"ha./'A.retz","e":"the/ earth","s":"H0776"},{"h":"כְּבוֹדֶֽ/ךָ׃","t":"ke.vo.De./kha","e":"glory/ your","s":"H3519"}],"6":[{"h":"רֶ֤שֶׁת׀","t":"Re.shet","e":"a net","s":"H7568"},{"h":"הֵכִ֣ינוּ","t":"he.Khi.nu","e":"they prepared","s":"H3559"},{"h":"לִ/פְעָמַ/י֮","t":"li/f.'a.Ma/i","e":"for/ feet/ my","s":"H6471"},{"h":"כָּפַ֪ף","t":"ka.Faf","e":"it bent down","s":"H3721"},{"h":"נַ֫פְשִׁ֥/י","t":"naf.Sh/i","e":"self/ my","s":"H5315"},{"h":"כָּר֣וּ","t":"ka.Ru","e":"they dug","s":"H3738"},{"h":"לְ/פָנַ֣/י","t":"le./fa.Na/i","e":"/ before/ me","s":"H6440"},{"h":"שִׁיחָ֑ה","t":"shi.Chah","e":"a pit","s":"H7882"},{"h":"נָפְל֖וּ","t":"na.fe.Lu","e":"they have fallen","s":"H5307"},{"h":"בְ/תוֹכָ֣/הּ","t":"ve./to.Kha/h","e":"in/ [the] midst of/ it","s":"H8432"},{"h":"סֶֽלָה׃","t":"Se.lah","e":"Selah","s":"H5542"}],"7":[{"h":"נָ֘כ֤וֹן","t":"na.Khon","e":"[is] steadfast","s":"H3559"},{"h":"לִבִּ֣/י","t":"li.B/i","e":"heart/ my","s":"H3820"},{"h":"אֱ֭לֹהִים","t":"'E.lo.Him","e":"O God","s":"H0430"},{"h":"נָכ֣וֹן","t":"na.Khon","e":"[is] steadfast","s":"H3559"},{"h":"לִבִּ֑/י","t":"li.B/i","e":"heart/ my","s":"H3820"},{"h":"אָ֝שִׁ֗ירָה","t":"'a.Shi.rah","e":"I will sing","s":"H7891"},{"h":"וַ/אֲזַמֵּֽרָה׃","t":"va./'a.za.Me.rah","e":"and/ I will sing praises","s":"H2167"}],"8":[{"h":"ע֤וּרָ/ה","t":"'U.ra/h","e":"awake/ !","s":"H5782"},{"h":"כְבוֹדִ֗/י","t":"khe.vo.D/i","e":"O honor/ my","s":"H3519"},{"h":"ע֭וּרָֽ/ה","t":"'U.ra/h","e":"awake/ !","s":"H5782"},{"h":"הַ/נֵּ֥בֶל","t":"ha./Ne.vel","e":"O/ lyre","s":"H5035"},{"h":"וְ/כִנּ֗וֹר","t":"ve./khi.Nor","e":"and/ harp","s":"H3658"},{"h":"אָעִ֥ירָה","t":"'a.'I.rah","e":"I will waken","s":"H5782"},{"h":"שָּֽׁחַר׃","t":"Sha.char","e":"[the] dawn","s":"H7837"}],"9":[{"h":"אוֹדְ/ךָ֖","t":"'od./Kha","e":"I will give thanks to/ you","s":"H3034"},{"h":"בָ/עַמִּ֥ים׀","t":"va./'a.Mim","e":"among the/ peoples","s":"H5971"},{"h":"אֲדֹנָ֑י","t":"'a.do.Nai","e":"O Lord","s":"H0136"},{"h":"אֲ֝זַמֶּרְ/ךָ֗","t":"'a.za.mer./kha","e":"I will sing praises to/ you","s":"H2167"},{"h":"בַּל־","t":"bal-","e":"not","s":"H1077"},{"h":"אֻמִּֽים׃","t":"'u.Mim","e":"nations","s":"H0523"}],"10":[{"h":"כִּֽי־","t":"ki-","e":"for","s":"H3588"},{"h":"גָדֹ֣ל","t":"ga.Dol","e":"[is] great","s":"H1419"},{"h":"עַד־","t":"'ad-","e":"to","s":"H5704"},{"h":"שָׁמַ֣יִם","t":"sha.Ma.yim","e":"[the] heavens","s":"H8064"},{"h":"חַסְדֶּ֑/ךָ","t":"chas.De./kha","e":"covenant loyalty/ your","s":"H2617"},{"h":"וְֽ/עַד־","t":"ve./'ad-","e":"and/ to","s":"H5704"},{"h":"שְׁחָקִ֥ים","t":"she.cha.Kim","e":"[the] clouds","s":"H7834"},{"h":"אֲמִתֶּֽ/ךָ׃","t":"'a.mi.Te./kha","e":"faithfulness/ your","s":"H0571"}],"11":[{"h":"ר֣וּמָ/ה","t":"Ru.ma/h","e":"be exalted/ !","s":"H7311"},{"h":"עַל־","t":"'al-","e":"above","s":"H5921"},{"h":"שָׁמַ֣יִם","t":"sha.Ma.yim","e":"[the] heavens","s":"H8064"},{"h":"אֱלֹהִ֑ים","t":"'E.lo.Him","e":"O God","s":"H0430"},{"h":"עַ֖ל","t":"'al","e":"[be] over","s":"H5921"},{"h":"כָּל־","t":"kol-","e":"all","s":"H3605"},{"h":"הָ/אָ֣רֶץ","t":"ha./'A.retz","e":"the/ earth","s":"H0776"},{"h":"כְּבוֹדֶֽ/ךָ׃","t":"ke.vo.De./kha","e":"glory/ your","s":"H3519"}]}